clarku_youtube_crawler/ChannelCrawler.py
clarku_youtube_crawler/CrawlerObject.py
clarku_youtube_crawler/JSONDecoder.py
clarku_youtube_crawler/RawCrawler.py
clarku_youtube_crawler/SubtitleCrawler.py
clarku_youtube_crawler/US_CATE.json
clarku_youtube_crawler/__init__.py
clarku_youtube_crawler-2.1.3.dist-info/LICENSE
clarku_youtube_crawler-2.1.3.dist-info/METADATA
clarku_youtube_crawler-2.1.3.dist-info/WHEEL
clarku_youtube_crawler-2.1.3.dist-info/dependency_links.txt
clarku_youtube_crawler-2.1.3.dist-info/top_level.txt
clarku_youtube_crawler-2.1.3.dist-info/RECORD
