Metadata-Version: 2.1
Name: clarku-youtube-crawler
Version: 2.1.3
Summary: Clark University, Package for YouTube crawler and cleaning data
Home-page: https://github.com/ClarkUniversity-NiuLab/clarku-youtube-crawler
Author: Shuo Niu
Author-email: ShNiu@clarku.edu
License: UNKNOWN
Platform: UNKNOWN
Classifier: Programming Language :: Python :: 3
Classifier: License :: OSI Approved :: MIT License
Classifier: Operating System :: OS Independent
Requires-Python: >=3.6
License-File: LICENSE
Requires-Dist: configparser
Requires-Dist: datetime
Requires-Dist: pytz
Requires-Dist: pandas
Requires-Dist: isodate
Requires-Dist: xlrd
Requires-Dist: youtube-transcript-api
Requires-Dist: google-api-python-client
